api_res_py/__init__.py
api_res_py/as_api_res.py
api_res_py-0.1.dist-info/LICENSE
api_res_py-0.1.dist-info/METADATA
api_res_py-0.1.dist-info/WHEEL
api_res_py-0.1.dist-info/dependency_links.txt
api_res_py-0.1.dist-info/top_level.txt
api_res_py-0.1.dist-info/RECORD
